dircraft/__init__.py
dircraft/cli.py
dircraft/generator.py
dircraft/gui.py
dircraft/parser.py
dircraft-0.1.0.dist-info/licenses/LICENSE
tests/__init__.py
tests/test_generator.py
tests/test_parser.py
dircraft-0.1.0.dist-info/METADATA
dircraft-0.1.0.dist-info/WHEEL
dircraft-0.1.0.dist-info/entry_points.txt
dircraft-0.1.0.dist-info/top_level.txt
dircraft-0.1.0.dist-info/RECORD
