Metadata-Version: 2.4
Name: dircraft
Version: 0.1.0
Summary: A tool to generate project directory structures from specifications.
Home-page: https://github.com/Whiteflakes/dircraft
Author: Whiteflakes
Author-email: whiteflakesdev@gmail.com
Classifier: Programming Language :: Python :: 3
Classifier: License :: OSI Approved :: MIT License
Classifier: Operating System :: OS Independent
Requires-Python: >=3.6
License-File: LICENSE
Requires-Dist: pyyaml
Requires-Dist: click
Dynamic: author
Dynamic: author-email
Dynamic: classifier
Dynamic: description
Dynamic: description-content-type
Dynamic: home-page
Dynamic: license-file
Dynamic: requires-dist
Dynamic: requires-python
Dynamic: summary
